README.md
mini_backtest/__init__.py
mini_backtest/backtester.py
mini_backtest/data.py
mini_backtest/data_loader.py
mini_backtest/indicators.py
mini_backtest/metrics.py
mini_backtest/portfolio.py
mini_backtest/signals.py
mini_backtest/simple.py
mini_backtest/simulator.py
mini_backtest/strategy.py
mini_backtest-0.1.6.dist-info/METADATA
mini_backtest-0.1.6.dist-info/WHEEL
mini_backtest-0.1.6.dist-info/RECORD
