Metadata-Version: 2.4
Name: mini_backtest
Version: 0.1.6
Summary: A minimal, extensible backtesting toolkit (CAGR, Max Drawdown).
Author: Mini Backtest Maintainers
Keywords: backtest,finance,numpy,pandas,trading
Classifier: Intended Audience :: Developers
Classifier: Intended Audience :: Financial and Insurance Industry
Classifier: Programming Language :: Python :: 3
Classifier: Programming Language :: Python :: 3 :: Only
Classifier: Programming Language :: Python :: 3.8
Classifier: Programming Language :: Python :: 3.9
Classifier: Programming Language :: Python :: 3.10
Classifier: Programming Language :: Python :: 3.11
Classifier: Programming Language :: Python :: 3.12
Classifier: Topic :: Office/Business :: Financial :: Investment
Requires-Python: >=3.8
Requires-Dist: numpy>=1.22
Requires-Dist: pandas>=1.4
